mlflow_yarn/__init__.py
mlflow_yarn/_upload_logs.py
mlflow_yarn/_version.py
mlflow_yarn/yarn_backend.py
mlflow_yarn-0.0.1.dist-info/LICENSE
mlflow_yarn-0.0.1.dist-info/METADATA
mlflow_yarn-0.0.1.dist-info/WHEEL
mlflow_yarn-0.0.1.dist-info/entry_points.txt
mlflow_yarn-0.0.1.dist-info/top_level.txt
mlflow_yarn-0.0.1.dist-info/RECORD
