Metadata-Version: 2.1
Name: mlflow-yarn
Version: 0.0.1
Summary: Backend implementation for running MLFlow projects on Hadoop/YARN
Home-page: https://github.com/criteo/mlflow-yarn
Maintainer: Criteo
Maintainer-email: github@criteo.com
License: UNKNOWN
Keywords: mlflow
Platform: UNKNOWN
Classifier: Development Status :: 4 - Beta
Classifier: Intended Audience :: Developers
Classifier: Intended Audience :: Science/Research
Classifier: Operating System :: OS Independent
Classifier: License :: OSI Approved :: Apache Software License
Classifier: Programming Language :: Python :: 3
Classifier: Programming Language :: Python :: 3.6
Classifier: Programming Language :: Python :: 3.7
Classifier: Topic :: Software Development :: Libraries
Requires-Python: >=3.6
Requires-Dist: cluster-pack
Requires-Dist: skein
Requires-Dist: mlflow
